{"nodes": [{"id": "authapi", "label": "AuthApi.kt", "file_type": "code", "source_file": "core/sdk/src/commonMain/kotlin/com/m2f/template/sdk/api/AuthApi.kt", "source_location": "L1"}, {"id": "authapi_authapi", "label": "AuthApi", "file_type": "code", "source_file": "core/sdk/src/commonMain/kotlin/com/m2f/template/sdk/api/AuthApi.kt", "source_location": "L19"}, {"id": "authapi_authapi_register", "label": ".register()", "file_type": "code", "source_file": "core/sdk/src/commonMain/kotlin/com/m2f/template/sdk/api/AuthApi.kt", "source_location": "L20"}, {"id": "authapi_authapi_login", "label": ".login()", "file_type": "code", "source_file": "core/sdk/src/commonMain/kotlin/com/m2f/template/sdk/api/AuthApi.kt", "source_location": "L21"}, {"id": "authapi_authapi_refresh", "label": ".refresh()", "file_type": "code", "source_file": "core/sdk/src/commonMain/kotlin/com/m2f/template/sdk/api/AuthApi.kt", "source_location": "L22"}, {"id": "authapi_authapi_forgotpassword", "label": ".forgotPassword()", "file_type": "code", "source_file": "core/sdk/src/commonMain/kotlin/com/m2f/template/sdk/api/AuthApi.kt", "source_location": "L23"}, {"id": "authapi_authapi_resetpassword", "label": ".resetPassword()", "file_type": "code", "source_file": "core/sdk/src/commonMain/kotlin/com/m2f/template/sdk/api/AuthApi.kt", "source_location": "L24"}, {"id": "authapi_authapi_logout", "label": ".logout()", "file_type": "code", "source_file": "core/sdk/src/commonMain/kotlin/com/m2f/template/sdk/api/AuthApi.kt", "source_location": "L25"}], "edges": [{"source": "authapi", "target": "authapi_authapi", "relation": "contains", "confidence": "EXTRACTED", "source_file": "core/sdk/src/commonMain/kotlin/com/m2f/template/sdk/api/AuthApi.kt", "source_location": "L19", "weight": 1.0}, {"source": "authapi_authapi", "target": "authapi_authapi_register", "relation": "method", "confidence": "EXTRACTED", "source_file": "core/sdk/src/commonMain/kotlin/com/m2f/template/sdk/api/AuthApi.kt", "source_location": "L20", "weight": 1.0}, {"source": "authapi_authapi", "target": "authapi_authapi_login", "relation": "method", "confidence": "EXTRACTED", "source_file": "core/sdk/src/commonMain/kotlin/com/m2f/template/sdk/api/AuthApi.kt", "source_location": "L21", "weight": 1.0}, {"source": "authapi_authapi", "target": "authapi_authapi_refresh", "relation": "method", "confidence": "EXTRACTED", "source_file": "core/sdk/src/commonMain/kotlin/com/m2f/template/sdk/api/AuthApi.kt", "source_location": "L22", "weight": 1.0}, {"source": "authapi_authapi", "target": "authapi_authapi_forgotpassword", "relation": "method", "confidence": "EXTRACTED", "source_file": "core/sdk/src/commonMain/kotlin/com/m2f/template/sdk/api/AuthApi.kt", "source_location": "L23", "weight": 1.0}, {"source": "authapi_authapi", "target": "authapi_authapi_resetpassword", "relation": "method", "confidence": "EXTRACTED", "source_file": "core/sdk/src/commonMain/kotlin/com/m2f/template/sdk/api/AuthApi.kt", "source_location": "L24", "weight": 1.0}, {"source": "authapi_authapi", "target": "authapi_authapi_logout", "relation": "method", "confidence": "EXTRACTED", "source_file": "core/sdk/src/commonMain/kotlin/com/m2f/template/sdk/api/AuthApi.kt", "source_location": "L25", "weight": 1.0}]}